intime_sdk/__init__.py
intime_sdk/core/__init__.py
intime_sdk/core/base.py
intime_sdk/core/constants.py
intime_sdk/core/error_map.py
intime_sdk/intime/__init__.py
intime_sdk/intime/constants.py
intime_sdk/intime/send_messages.py
intime_sdk-1.0.2.dist-info/LICENSE
intime_sdk-1.0.2.dist-info/METADATA
intime_sdk-1.0.2.dist-info/WHEEL
intime_sdk-1.0.2.dist-info/top_level.txt
intime_sdk-1.0.2.dist-info/RECORD
